txt_utils/__init__.py
txt_utils/helper.py
txt_utils/py.typed
txt_utils/replacement.py
txt_utils/statistics_unit_counts.py
txt_utils/transcription.py
txt_utils/vocabulary_exporting.py
txt_utils_cli/__init__.py
txt_utils_cli/cli.py
txt_utils_cli/default_args.py
txt_utils_cli/globals.py
txt_utils_cli/helper.py
txt_utils_cli/line_replacement.py
txt_utils_cli/logging_configuration.py
txt_utils_cli/merging.py
txt_utils_cli/py.typed
txt_utils_cli/replacement.py
txt_utils_cli/statistics_unit_counts.py
txt_utils_cli/transcription.py
txt_utils_cli/trimming.py
txt_utils_cli/unit_removal.py
txt_utils_cli/vocabulary_exporting.py
txt_utils-0.0.3.dist-info/LICENSE
txt_utils-0.0.3.dist-info/METADATA
txt_utils-0.0.3.dist-info/WHEEL
txt_utils-0.0.3.dist-info/entry_points.txt
txt_utils-0.0.3.dist-info/top_level.txt
txt_utils-0.0.3.dist-info/RECORD
